setup.py
tm1637.py
micropython_tm1637.egg-info/PKG-INFO
micropython_tm1637.egg-info/SOURCES.txt
micropython_tm1637.egg-info/dependency_links.txt
micropython_tm1637.egg-info/top_level.txt