Metadata-Version: 1.1
Name: micropython-tm1637
Version: 1.3.0
Summary: MicroPython library for TM1637 LED driver.
Home-page: https://github.com/mcauser/micropython-tm1637
Author: Mike Causer
Author-email: mcauser@gmail.com
License: MIT
Keywords: tm1637 seven segment led micropython
Platform: UNKNOWN
Classifier: Development Status :: 5 - Production/Stable
Classifier: Programming Language :: Python :: Implementation :: MicroPython
Classifier: License :: OSI Approved :: MIT License
